{
"meta":{"test_sets":[],"test_metrics":[],"learn_metrics":[{"best_value":"Min","name":"RMSE"}],"launch_mode":"Train","parameters":"","iteration_count":100,"learn_sets":["learn"],"name":"experiment"},
"iterations":[
{"learn":[14.005006],"iteration":0,"passed_time":0.0007969244458,"remaining_time":0.07889552013},
{"learn":[13.14441192],"iteration":1,"passed_time":0.001558061728,"remaining_time":0.07634502469},
{"learn":[12.34258257],"iteration":2,"passed_time":0.002187545177,"remaining_time":0.0707306274},
{"learn":[11.64527793],"iteration":3,"passed_time":0.002822104453,"remaining_time":0.06773050688},
{"learn":[11.02766183],"iteration":4,"passed_time":0.003481544935,"remaining_time":0.06614935377},
{"learn":[10.43485794],"iteration":5,"passed_time":0.004204098963,"remaining_time":0.06586421709},
{"learn":[9.890641275],"iteration":6,"passed_time":0.004889837524,"remaining_time":0.06496498425},
{"learn":[9.492161212],"iteration":7,"passed_time":0.005575034492,"remaining_time":0.06411289666},
{"learn":[9.105082953],"iteration":8,"passed_time":0.006317385887,"remaining_time":0.06387579064},
{"learn":[8.674157135],"iteration":9,"passed_time":0.006907579849,"remaining_time":0.06216821864},
{"learn":[8.341743544],"iteration":10,"passed_time":0.007536890645,"remaining_time":0.06098029704},
{"learn":[8.049372916],"iteration":11,"passed_time":0.008164944002,"remaining_time":0.05987625601},
{"learn":[7.757318612],"iteration":12,"passed_time":0.008792590363,"remaining_time":0.05884272012},
{"learn":[7.522206899],"iteration":13,"passed_time":0.009450784621,"remaining_time":0.05805481981},
{"learn":[7.297756655],"iteration":14,"passed_time":0.01006212552,"remaining_time":0.0570187113},
{"learn":[7.088359431],"iteration":15,"passed_time":0.01066870947,"remaining_time":0.0560107247},
{"learn":[6.882113791],"iteration":16,"passed_time":0.0112551956,"remaining_time":0.05495183736},
{"learn":[6.704728832],"iteration":17,"passed_time":0.01186332541,"remaining_time":0.05404403797},
{"learn":[6.563881962],"iteration":18,"passed_time":0.01247285686,"remaining_time":0.05317375821},
{"learn":[6.418790279],"iteration":19,"passed_time":0.01309472397,"remaining_time":0.05237889587},
{"learn":[6.315756953],"iteration":20,"passed_time":0.01357604182,"remaining_time":0.05107177639},
{"learn":[6.210157751],"iteration":21,"passed_time":0.01415436081,"remaining_time":0.05018364287},
{"learn":[6.115058449],"iteration":22,"passed_time":0.01481071478,"remaining_time":0.04958369729},
{"learn":[6.014819884],"iteration":23,"passed_time":0.01539334247,"remaining_time":0.04874558448},
{"learn":[5.93117229],"iteration":24,"passed_time":0.01615604444,"remaining_time":0.04846813332},
{"learn":[5.844857622],"iteration":25,"passed_time":0.01689631639,"remaining_time":0.04808951588},
{"learn":[5.771145213],"iteration":26,"passed_time":0.01785028582,"remaining_time":0.04826188389},
{"learn":[5.704018229],"iteration":27,"passed_time":0.01858332599,"remaining_time":0.04778569541},
{"learn":[5.665806474],"iteration":28,"passed_time":0.01923179562,"remaining_time":0.04708474101},
{"learn":[5.616500369],"iteration":29,"passed_time":0.02019141011,"remaining_time":0.04711329027},
{"learn":[5.558023666],"iteration":30,"passed_time":0.02127248392,"remaining_time":0.04734843196},
{"learn":[5.510080976],"iteration":31,"passed_time":0.02202265436,"remaining_time":0.04679814051},
{"learn":[5.468747792],"iteration":32,"passed_time":0.02280297691,"remaining_time":0.04629695313},
{"learn":[5.429275534],"iteration":33,"passed_time":0.02354652566,"remaining_time":0.04570796158},
{"learn":[5.402117324],"iteration":34,"passed_time":0.02432222866,"remaining_time":0.04516985322},
{"learn":[5.367635151],"iteration":35,"passed_time":0.0250630406,"remaining_time":0.04455651662},
{"learn":[5.345181232],"iteration":36,"passed_time":0.02577886358,"remaining_time":0.04389374069},
{"learn":[5.319151269],"iteration":37,"passed_time":0.02646228835,"remaining_time":0.04317531258},
{"learn":[5.296134146],"iteration":38,"passed_time":0.02713198144,"remaining_time":0.04243720173},
{"learn":[5.269629003],"iteration":39,"passed_time":0.02782153197,"remaining_time":0.04173229796},
{"learn":[5.251147059],"iteration":40,"passed_time":0.02843611843,"remaining_time":0.04092026798},
{"learn":[5.248003302],"iteration":41,"passed_time":0.02870409092,"remaining_time":0.0396389827},
{"learn":[5.232376509],"iteration":42,"passed_time":0.02956088416,"remaining_time":0.03918535808},
{"learn":[5.213524255],"iteration":43,"passed_time":0.03026339767,"remaining_time":0.03851705158},
{"learn":[5.189691584],"iteration":44,"passed_time":0.03098455525,"remaining_time":0.03787001198},
{"learn":[5.166052198],"iteration":45,"passed_time":0.03216644337,"remaining_time":0.03776060744},
{"learn":[5.140406659],"iteration":46,"passed_time":0.0332583963,"remaining_time":0.03750414902},
{"learn":[5.118929684],"iteration":47,"passed_time":0.03403476867,"remaining_time":0.03687099939},
{"learn":[5.108792602],"iteration":48,"passed_time":0.03466233011,"remaining_time":0.03607711909},
{"learn":[5.098141225],"iteration":49,"passed_time":0.03532631764,"remaining_time":0.03532631764},
{"learn":[5.085926393],"iteration":50,"passed_time":0.03595450359,"remaining_time":0.03454452306},
{"learn":[5.067816804],"iteration":51,"passed_time":0.03671601382,"remaining_time":0.03389170507},
{"learn":[5.049834901],"iteration":52,"passed_time":0.0373980061,"remaining_time":0.03316426956},
{"learn":[5.03838627],"iteration":53,"passed_time":0.03806502848,"remaining_time":0.032425765},
{"learn":[5.033534248],"iteration":54,"passed_time":0.03847113549,"remaining_time":0.03147638358},
{"learn":[5.023726885],"iteration":55,"passed_time":0.03926212925,"remaining_time":0.03084881584},
{"learn":[5.01290392],"iteration":56,"passed_time":0.03984268511,"remaining_time":0.03005676245},
{"learn":[5.005569127],"iteration":57,"passed_time":0.04042207647,"remaining_time":0.02927115882},
{"learn":[4.989969032],"iteration":58,"passed_time":0.04097719431,"remaining_time":0.0284756774},
{"learn":[4.976762446],"iteration":59,"passed_time":0.0416230409,"remaining_time":0.02774869393},
{"learn":[4.967222715],"iteration":60,"passed_time":0.04217199051,"remaining_time":0.02696242016},
{"learn":[4.954407599],"iteration":61,"passed_time":0.04276307778,"remaining_time":0.02620962832},
{"learn":[4.942125056],"iteration":62,"passed_time":0.0433591219,"remaining_time":0.02546488112},
{"learn":[4.930230716],"iteration":63,"passed_time":0.04394944004,"remaining_time":0.02472156002},
{"learn":[4.921695642],"iteration":64,"passed_time":0.0445185828,"remaining_time":0.02397154459},
{"learn":[4.906405625],"iteration":65,"passed_time":0.04507109403,"remaining_time":0.02321844238},
{"learn":[4.894330248],"iteration":66,"passed_time":0.04560538499,"remaining_time":0.0224623538},
{"learn":[4.88211557],"iteration":67,"passed_time":0.04651024297,"remaining_time":0.02188717316},
{"learn":[4.877946398],"iteration":68,"passed_time":0.04744942035,"remaining_time":0.02131785552},
{"learn":[4.863182126],"iteration":69,"passed_time":0.04813074926,"remaining_time":0.02062746397},
{"learn":[4.84646533],"iteration":70,"passed_time":0.04875157444,"remaining_time":0.01991261491},
{"learn":[4.838014752],"iteration":71,"passed_time":0.04936869781,"remaining_time":0.01919893804},
{"learn":[4.82981137],"iteration":72,"passed_time":0.04994186886,"remaining_time":0.01847165013},
{"learn":[4.817094767],"iteration":73,"passed_time":0.05057159106,"remaining_time":0.01776839686},
{"learn":[4.808314151],"iteration":74,"passed_time":0.05113684853,"remaining_time":0.01704561618},
{"learn":[4.796235023],"iteration":75,"passed_time":0.05169016734,"remaining_time":0.01632321074},
{"learn":[4.784434534],"iteration":76,"passed_time":0.05234136216,"remaining_time":0.01563443285},
{"learn":[4.774402487],"iteration":77,"passed_time":0.05291594928,"remaining_time":0.01492501134},
{"learn":[4.76731896],"iteration":78,"passed_time":0.05351321199,"remaining_time":0.01422503103},
{"learn":[4.75934113],"iteration":79,"passed_time":0.05409630195,"remaining_time":0.01352407549},
{"learn":[4.754106378],"iteration":80,"passed_time":0.0546046101,"remaining_time":0.01280848879},
{"learn":[4.744002932],"iteration":81,"passed_time":0.05521893537,"remaining_time":0.01212122972},
{"learn":[4.731700554],"iteration":82,"passed_time":0.0557348158,"remaining_time":0.01141556468},
{"learn":[4.723284153],"iteration":83,"passed_time":0.05629774306,"remaining_time":0.01072337963},
{"learn":[4.712232782],"iteration":84,"passed_time":0.05703373355,"remaining_time":0.01006477651},
{"learn":[4.703046867],"iteration":85,"passed_time":0.05763026559,"remaining_time":0.009381671142},
{"learn":[4.698601855],"iteration":86,"passed_time":0.05820287261,"remaining_time":0.008696980965},
{"learn":[4.692429407],"iteration":87,"passed_time":0.05878121043,"remaining_time":0.008015619604},
{"learn":[4.675027364],"iteration":88,"passed_time":0.05937710673,"remaining_time":0.007338743529},
{"learn":[4.662368584],"iteration":89,"passed_time":0.06002616723,"remaining_time":0.006669574136},
{"learn":[4.646206172],"iteration":90,"passed_time":0.06061658752,"remaining_time":0.005995047117},
{"learn":[4.641245848],"iteration":91,"passed_time":0.0613125935,"remaining_time":0.00533152987},
{"learn":[4.633900435],"iteration":92,"passed_time":0.06216677012,"remaining_time":0.004679219256},
{"learn":[4.624738236],"iteration":93,"passed_time":0.06298390173,"remaining_time":0.004020249047},
{"learn":[4.612798287],"iteration":94,"passed_time":0.06355579852,"remaining_time":0.003345042027},
{"learn":[4.605222001],"iteration":95,"passed_time":0.0641147007,"remaining_time":0.002671445862},
{"learn":[4.601725912],"iteration":96,"passed_time":0.06470602391,"remaining_time":0.002001217234},
{"learn":[4.59722371],"iteration":97,"passed_time":0.06523545016,"remaining_time":0.001331335717},
{"learn":[4.580235665],"iteration":98,"passed_time":0.06573858193,"remaining_time":0.0006640260801},
{"learn":[4.57591791],"iteration":99,"passed_time":0.06632484855,"remaining_time":0}
]}